furo50/__init__.py
furo50/py.typed
furo50/_static/css/cs50.css
furo50/_static/css/furo50_scaffold.css
furo50/_static/css/headings-underline.css
furo50/_static/css/hide-all-toc.css
furo50/_static/css/sidebar-scroll.css
furo50/_static/js/marker.js
furo50/_templates/page.html
furo50-1.0.0b2.dist-info/licenses/LICENSE
furo50-1.0.0b2.dist-info/WHEEL
furo50-1.0.0b2.dist-info/METADATA
furo50-1.0.0b2.dist-info/RECORD
