Metadata-Version: 2.4
Name: furo50
Version: 1.0.0b2
Summary: Sphinx Extension that turns furo theme into CS50's theme.
Keywords: documentation,sphinx,CS50
Author-email: ABD-01 <myac931@gmail.com>
Classifier: Development Status :: 4 - Beta
Classifier: Framework :: Sphinx :: Extension
Classifier: Intended Audience :: Developers
Classifier: License :: OSI Approved :: GNU General Public License v3 (GPLv3)
Classifier: Programming Language :: Python
Classifier: Programming Language :: Python :: 3 :: Only
Classifier: Programming Language :: Python :: 3.7
Classifier: Programming Language :: Python :: 3.8
Classifier: Programming Language :: Python :: 3.9
Classifier: Programming Language :: Python :: 3.10
Classifier: Programming Language :: Python :: 3.11
Classifier: Programming Language :: Python :: 3.12
Classifier: Topic :: Software Development :: Documentation
Classifier: Topic :: Documentation :: Sphinx
Classifier: Environment :: Plugins
Classifier: Environment :: Web Environment
License-File: LICENSE
Requires-Dist: sphinx>=7.1
Requires-Dist: furo<=2024.7.18
Requires-Dist: myst-parser ; extra == "docs"
Requires-Dist: sphinx-design ; extra == "docs"
Requires-Dist: sphinx-copybutton ; extra == "docs"
Project-URL: Homepage, https://github.com/ABD-01/furo50
Provides-Extra: docs
